ntx_python/__config__.py
ntx_python/__init__.py
ntx_python/__main__.py
ntx_python/__main_token__.py
ntx_python/ntx_auth_metadata_plugin.py
ntx_python/ntx_stt.py
ntx_python/ntx_protobuf/__init__.py
ntx_python/ntx_protobuf/engine_pb2.py
ntx_python/ntx_protobuf/engine_pb2_grpc.py
ntx_python-1.1.4.dist-info/METADATA
ntx_python-1.1.4.dist-info/WHEEL
ntx_python-1.1.4.dist-info/top_level.txt
ntx_python-1.1.4.dist-info/RECORD
