Metadata-Version: 2.1
Name: ntx-python
Version: 1.1.4
Summary: Python library for speech to text using NanoTrix cloud
Home-page: https://gitlab.com/nanogrid-libs/ntx-python
Author: Goheeca
Author-email: goheeca@gmail.com
License: UNKNOWN
Platform: UNKNOWN
Classifier: Programming Language :: Python :: 3
Classifier: License :: OSI Approved :: MIT License
Classifier: Operating System :: OS Independent
Requires-Python: >=3.6
Requires-Dist: grpcio (~=1.30.0)
Requires-Dist: aiohttp (~=3.6.2)
